python_qube_heatpump/__init__.py
python_qube_heatpump/client.py
python_qube_heatpump/const.py
python_qube_heatpump/models.py
python_qube_heatpump/py.typed
python_qube_heatpump/entities/__init__.py
python_qube_heatpump/entities/base.py
python_qube_heatpump/entities/binary_sensors.py
python_qube_heatpump/entities/sensors.py
python_qube_heatpump/entities/switches.py
python_qube_heatpump-1.4.7.dist-info/METADATA
python_qube_heatpump-1.4.7.dist-info/WHEEL
python_qube_heatpump-1.4.7.dist-info/licenses/LICENSE
python_qube_heatpump-1.4.7.dist-info/RECORD
