Metadata-Version: 2.4
Name: python-qube-heatpump
Version: 1.4.7
Summary: Async Modbus client for Qube Heat Pumps
Project-URL: Homepage, https://github.com/MattieGit/python-qube-heatpump
Project-URL: Bug Tracker, https://github.com/MattieGit/python-qube-heatpump/issues
Author-email: MattieGit <6250046+MattieGit@users.noreply.github.com>
License-File: LICENSE
Classifier: License :: OSI Approved :: MIT License
Classifier: Operating System :: OS Independent
Classifier: Programming Language :: Python :: 3
Requires-Python: >=3.12
Requires-Dist: pymodbus>=3.11.0
Provides-Extra: test
Requires-Dist: pytest; extra == 'test'
Requires-Dist: pytest-asyncio; extra == 'test'
Requires-Dist: pytest-mock; extra == 'test'
